[
    {
        "company_name": "Uber",
        "job_position": "back-end developer",
        "job_status": "applied",
        "job_comment": "Uber’s engineers primarily write in Python, Node.js, Go, and Java.",
        "label": "applied",
        "offer_amount": "",
        "application_data": "2021-08-18",
        "interview_date": "",
        "company_logo": "https://logo.clearbit.com/uber.com",
        "company_url": "https://uber.com",
        "user_id": "611ddc94ea96134536a88605"
    },
    {
        "company_name": "Netflix",
        "job_position": "back-end developer",
        "job_status": "priority",
        "job_comment": "The core operational infrastructure of Netflix has all been built in Java.",
        "label": "priority",
        "offer_amount": "",
        "application_data": "2021-08-18",
        "interview_date": "",
        "company_logo": "https://logo.clearbit.com/netflix.com",
        "company_url": "https://netflix.com",
        "user_id": "611ddc94ea96134536a88605"
    },
    {
        "company_name": "Google",
        "job_position": "front-end developer",
        "job_status": "interview",
        "job_comment": "Google uses four key programming languages: Python, Javascript, C++ and Java",
        "label": "interview",
        "offer_amount": "",
        "application_data": "2021-08-18",
        "interview_date": "2021-09-01",
        "company_logo": "https://logo.clearbit.com/google.com",
        "company_url": "https://google.com",
        "user_id": "611ddc94ea96134536a88606"
    },
    {
        "company_name": "Apple",
        "job_position": "full stack developer",
        "job_status": "offer",
        "job_comment": "Apple's primary programming language is Swift.",
        "label": "offer",
        "offer_amount": "90000",
        "application_data": "2021-08-10",
        "interview_date": "2021-08-18",
        "company_logo": "https://logo.clearbit.com/apple.com",
        "company_url": "https://apple.com",
        "user_id": "611ddc94ea96134536a88607"
        
    },
    {
        "company_name": "Amazon",
        "job_position": "back-end developer",
        "job_status": "inactive",
        "job_comment": "The official languages of Amazon are Python, Java, and Javascript",
        "label": "inactive",
        "offer_amount": "",
        "application_data": "2021-07-10",
        "interview_date": "2021-08-01",
        "company_logo": "https://logo.clearbit.com/amazon.com",
        "company_url": "https://amazon.com",
        "user_id": "611ddc94ea96134536a88607"
    }
]